LICENSE.md
README.md
pyproject.toml
setup.py
Mainframe3270/__init__.py
Mainframe3270/librarycomponent.py
Mainframe3270/py3270.py
Mainframe3270/utils.py
Mainframe3270/version.py
Mainframe3270/keywords/__init__.py
Mainframe3270/keywords/assertions.py
Mainframe3270/keywords/commands.py
Mainframe3270/keywords/connection.py
Mainframe3270/keywords/read_write.py
Mainframe3270/keywords/screenshot.py
Mainframe3270/keywords/wait_and_timeout.py
robotframework_mainframe3270.egg-info/PKG-INFO
robotframework_mainframe3270.egg-info/SOURCES.txt
robotframework_mainframe3270.egg-info/dependency_links.txt
robotframework_mainframe3270.egg-info/requires.txt
robotframework_mainframe3270.egg-info/top_level.txt