Metadata-Version: 2.2
Name: robotframework-mainframe3270
Version: 4.3
Summary: Mainframe Test library for Robot Framework
Home-page: https://github.com/MarketSquare/Robot-Framework-Mainframe-3270-Library
Author: Altran Portugal
Author-email: samuca@gmail.com
License: MIT License
Classifier: Development Status :: 5 - Production/Stable
Classifier: Framework :: Robot Framework
Classifier: Framework :: Robot Framework :: Library
Classifier: Intended Audience :: Developers
Classifier: License :: OSI Approved :: MIT License
Classifier: Operating System :: OS Independent
Classifier: Programming Language :: Python :: 3
Classifier: Programming Language :: Python :: 3 :: Only
Classifier: Topic :: Software Development :: Testing
Classifier: Topic :: Software Development :: Testing :: Acceptance
License-File: LICENSE.md
Requires-Dist: robotframework
Requires-Dist: robotframework-pythonlibcore
Requires-Dist: html2image
Dynamic: author
Dynamic: author-email
Dynamic: classifier
Dynamic: description
Dynamic: description-content-type
Dynamic: home-page
Dynamic: license
Dynamic: requires-dist
Dynamic: summary
